Metadata-Version: 1.1
Name: mirrorshield
Version: 0.0.1
Summary: mirrorshield
Home-page: https://github.com/vesche/mirrorshield
Author: Austin Jackson
Author-email: vesche@protonmail.com
License: MIT
Platform: UNKNOWN
Classifier: Development Status :: 1 - Planning
Classifier: License :: OSI Approved :: MIT License
Classifier: Programming Language :: Python :: 3
